aika/utilities/__init__.py
aika/utilities/freezing.py
aika/utilities/hashing.py
aika/utilities/pandas_lin_alg.py
aika/utilities/pandas_utils.py
aika/utilities/testing.py
aika/utilities/validators.py
aika/utilities/fin/__init__.py
aika/utilities/fin/brownian_motion.py
aika/utilities/fin/macd.py
aika/utilities/fin/returns.py
aika/utilities/fin/tests/__init__.py
aika/utilities/fin/tests/test_macd.py
aika/utilities/tests/__init__.py
aika/utilities/tests/test_freezing.py
aika/utilities/tests/test_pandas_lin_alg.py
aika/utilities/tests/test_pandas_utils.py
aika/utilities/tests/test_testing.py
aika/utilities/tests/test_validators.py
aika_utilities-1.0.0.dist-info/LICENSE.rst
aika_utilities-1.0.0.dist-info/METADATA
aika_utilities-1.0.0.dist-info/WHEEL
aika_utilities-1.0.0.dist-info/top_level.txt
aika_utilities-1.0.0.dist-info/RECORD
